articledata/__init__.py
articledata/article.py
articledata/py.typed
articledata/url.py
articledata-0.1.2.dist-info/LICENSE
articledata-0.1.2.dist-info/METADATA
articledata-0.1.2.dist-info/WHEEL
articledata-0.1.2.dist-info/namespace_packages.txt
articledata-0.1.2.dist-info/top_level.txt
articledata-0.1.2.dist-info/RECORD
